[
    {
        "id": "STAT-001",
        "category": "1変数データ",
        "question": "データに外れ値（極端な値）が含まれる場合、代表値として最も適切なのはどれか。",
        "choices": [
            "A. 平均値（アリスメティック平均）",
            "B. 中央値（メディアン）",
            "C. 最頻値（モード）",
            "D. 幾何平均"
        ],
        "answer_label": "B",
        "answer_index": 1,
        "explanation": "平均値は一部の極端な値（外れ値）の影響を大きく受けますが、中央値は外れ値に左右されにくい特性があります。そのため、外れ値を含む歪んだ分布では中央値を代表値とする方が適切です。"
    },
    {
        "id": "STAT-002",
        "category": "1変数データ",
        "question": "次のうち、データの散らばり（ばらつき）の程度を表す指標はどれか。",
        "choices": [
            "A. 平均値",
            "B. 中央値",
            "C. 分散",
            "D. 最頻値"
        ],
        "answer_label": "C",
        "answer_index": 2,
        "explanation": "分散はデータの散らばり具合を定量的に表す指標です。一方、平均値・中央値・最頻値はいずれもデータの中心的な値（代表値）を表す指標であり、散らばりを示す指標ではありません。"
    },
    {
        "id": "STAT-003",
        "category": "1変数データ",
        "question": "分散とは何を表す指標か。適切な説明を選べ。",
        "choices": [
            "A. データの各値と平均値との差の二乗の平均",
            "B. データの各値と平均値との差の平方根（標準偏差）のこと",
            "C. 最大値と最小値の差（範囲）のこと",
            "D. データの各値と中央値との差の平均（平均絶対偏差）のこと"
        ],
        "answer_label": "A",
        "answer_index": 0,
        "explanation": "分散は「各データの値と平均値との差」を二乗して平均した値です。分散が大きいほどデータのばらつきが大きいことを意味します（標準偏差は分散の正の平方根です）。"
    },
    {
        "id": "STAT-004",
        "category": "1変数データ",
        "question": "次のうち、箱ひげ図（ボックスプロット）における「箱」の長さに相当するものはどれか。",
        "choices": [
            "A. 四分位範囲（四分位偏差×2）",
            "B. データの全範囲（レンジ）",
            "C. 平均値 ± 1標準偏差の範囲",
            "D. 中央値の信頼区間"
        ],
        "answer_label": "A",
        "answer_index": 0,
        "explanation": "箱ひげ図の「箱」は第1四分位（Q1）から第3四分位（Q3）までを示しており、その長さは四分位範囲（IQR＝Q3−Q1）に対応します。"
    },
    {
        "id": "STAT-005",
        "category": "1変数データ",
        "question": "変動係数（CV: coefficient of variation）はどのような場面で有用な指標か。最も適切な選択肢を選べ。",
        "choices": [
            "A. 異なる平均値を持つ複数のデータ集団のばらつきを比較する場合",
            "B. データの分布が正規か歪んでいるかを判定する場合",
            "C. 2つの変数間の相関の強さを測定する場合",
            "D. アウトライヤー（外れ値）の有無を検出する場合"
        ],
        "answer_label": "A",
        "answer_index": 0,
        "explanation": "変動係数は「標準偏差を平均値で割った値」であり、データの相対的なばらつきを示します。平均値が異なるデータセット同士でも、変動係数を用いればばらつきを比較できます。"
    },
    {
        "id": "STAT-006",
        "category": "1変数データ",
        "question": "投資のリターンのように割合や成長率の平均を求めたい場合、適切な指標はどれか。",
        "choices": [
            "A. 算術平均（普通の平均値）",
            "B. 幾何平均",
            "C. 調和平均",
            "D. 中央値"
        ],
        "answer_label": "B",
        "answer_index": 1,
        "explanation": "成長率や比率の平均には幾何平均が適しています。例えば年ごとの増加率の平均を求める場合、各年の(1+増加率)の幾何平均−1を計算することで全体の平均増加率を求められます。"
    },
    {
        "id": "STAT-007",
        "category": "1変数データ",
        "question": "標準得点（Z得点）とは何か。正しい説明を選んでください。",
        "choices": [
            "A. データの値が平均からどれだけ離れているかを標準偏差単位で示した値",
            "B. データの値を0から1の範囲に正規化した値（百分位に相当）",
            "C. データの分布が標準正規分布に従うかどうかを示す統計量",
            "D. 母集団全体におけるその値の偏差の2乗和"
        ],
        "answer_label": "A",
        "answer_index": 0,
        "explanation": "標準得点（Z値）は、各データが平均から何標準偏差離れているかを表す指標です。Z得点により、異なる尺度のデータでも平均からの相対的な位置を比較できます。"
    },
    {
        "id": "STAT-008",
        "category": "1変数データ",
        "question": "歪度(ゆがみ度、スキューネス)が正の値をとる分布の形として適切なのはどれか。",
        "choices": [
            "A. 右に裾が長い分布（右に歪んだ分布）",
            "B. 左に裾が長い分布（左に歪んだ分布）",
            "C. 平均値＝中央値＝最頻値となる対称分布",
            "D. 二峰性の分布（山が2つある分布）"
        ],
        "answer_label": "A",
        "answer_index": 0,
        "explanation": "歪度が正のときは分布の右側（高い値側）に長い裾野を持つ、右に歪んだ分布を意味します。典型的には平均値が中央値より大きくなります。"
    },
    {
        "id": "STAT-009",
        "category": "1変数データ",
        "question": "移動平均（移動平均線）の主な目的として正しいものを選んでください。",
        "choices": [
            "A. 時系列データの短期的な変動を平滑化し、基調となるトレンドを把握しやすくするため",
            "B. 相関係数を計算するためにデータを標準化するため",
            "C. 時系列データの季節変動を完全に除去しデータを正規分布化するため",
            "D. 異なる系列間の因果関係を特定するための統計的検定を行うため"
        ],
        "answer_label": "A",
        "answer_index": 0,
        "explanation": "移動平均は、時系列データの短期的な変動をならして基本的な傾向（トレンド）を見るために用いられます。"
    },
    {
        "id": "STAT-010",
        "category": "1変数データ",
        "question": "基準年の数量をウエイト（重み）として当年の価格変動を測る指数はどれか。",
        "choices": [
            "A. ラスパイレス指数（Laspeyres指数）",
            "B. パーシェ指数（Paasche指数）",
            "C. フィッシャー指数（Fisher指数）",
            "D. 消費者物価指数（CPI）"
        ],
        "answer_label": "A",
        "answer_index": 0,
        "explanation": "ラスパイレス指数は基準時点（基準年）の数量を固定ウェイトとして用いる物価指数であり、物価の変動を測定します。"
    },
    {
        "id": "STAT-011",
        "category": "2変数データ",
        "question": "次の相関係数のうち、最も強い線形関係を示しているのはどれか。",
        "choices": [
            "A. +0.80",
            "B. -0.90",
            "C. +0.10",
            "D. -0.50"
        ],
        "answer_label": "B",
        "answer_index": 1,
        "explanation": "相関係数rの絶対値が大きいほど強い線形関係を意味します。+0.80と-0.90では、-0.90の方が絶対値が大きいため強い相関です。"
    },
    {
        "id": "STAT-012",
        "category": "2変数データ",
        "question": "ある2つの連続型変数XとYの相関係数が0である場合の解釈として正しいものはどれか。",
        "choices": [
            "A. XとYに直線的な関係がないことを意味する",
            "B. XとYに全く何の関係も存在しないことを意味する",
            "C. XとYが独立であることを意味する",
            "D. 計算に誤りがある可能性を意味する"
        ],
        "answer_label": "A",
        "answer_index": 0,
        "explanation": "相関係数が0である場合、直線的な関係（線形相関）が見られないことを示します。ただし、非線形の関係がある場合などはr=0となり得るため、「全く無関係」とは限りません。"
    },
    {
        "id": "STAT-013",
        "category": "2変数データ",
        "question": "次の記述のうち、相関係数に関する正しい説明はどれか。",
        "choices": [
            "A. 相関係数の範囲は -1 から +1 の間である",
            "B. 相関係数が大きいほど必ず因果関係が強いことを意味する",
            "C. 相関係数が0に近いほど2変数の関係は強いことを意味する",
            "D. 相関係数は外れ値の影響を受けない指標である"
        ],
        "answer_label": "A",
        "answer_index": 0,
        "explanation": "相関係数rは常に -1～+1 の範囲をとります。+1は完全な正の相関、-1は完全な負の相関、0は直線的な関係が無いことを示します。"
    },
    {
        "id": "STAT-014",
        "category": "2変数データ",
        "question": "クロス集計表（分割表）はどのようなデータの関係を分析するときに適切か。",
        "choices": [
            "A. 2つの質的（カテゴリー）変数間の関係を分析するとき",
            "B. 2つの数量（連続）変数間の関係を分析するとき",
            "C. 1つの変数の時系列変動を分析するとき",
            "D. 3つ以上の変数の同時関係を分析するとき"
        ],
        "answer_label": "A",
        "answer_index": 0,
        "explanation": "クロス集計表（分割表）は、2つの質的データ（カテゴリカル変数）の組み合わせによる度数をまとめた表です。"
    },
    {
        "id": "STAT-015",
        "category": "2変数データ",
        "question": "単回帰分析の回帰式 Y = a + bX において、回帰係数bの意味として正しいものはどれか。",
        "choices": [
            "A. Xが1単位増加したときに予測されるYの増加量（傾き）",
            "B. Xが0のときの予測されるYの値（切片）",
            "C. XとYの相関係数の値",
            "D. 回帰直線の当てはまりの良さ（決定係数）の値"
        ],
        "answer_label": "A",
        "answer_index": 0,
        "explanation": "回帰直線の傾きである係数bは、「Xが1増加したときにYが平均してどれだけ増減するか」を示します。"
    },
    {
        "id": "STAT-016",
        "category": "2変数データ",
        "question": "2つの独立な母集団の平均値の差を検定する際に適切な手法はどれか。",
        "choices": [
            "A. スチューデントのt検定（2標本のt検定）",
            "B. カイ二乗検定",
            "C. F検定",
            "D. Z検定"
        ],
        "answer_label": "A",
        "answer_index": 0,
        "explanation": "2つの群の平均の差の有意性を検定する場合、通常は2標本t検定（対応のないt検定）を用います。"
    },
    {
        "id": "STAT-017",
        "category": "2変数データ",
        "question": "回帰分析において、あるデータ点の残差（Residual）とは何か。正しい定義を選んでください。",
        "choices": [
            "A. 実際の観測値と回帰直線による予測値との差",
            "B. 観測されたデータの平均値からの偏差値",
            "C. データから算出される回帰係数の標準誤差",
            "D. 回帰モデルに説明変数を追加して増加する決定係数のこと"
        ],
        "answer_label": "A",
        "answer_index": 0,
        "explanation": "残差は回帰分析でモデルの当てはまりを評価するために用いられる量で、各データ点について「観測値 - 回帰式による予測値」で計算されます。"
    },
    {
        "id": "STAT-018",
        "category": "2変数データ",
        "question": "ブロッキング（Blocking）とは実験計画における手法の一つである。ブロック化の目的として正しいものを選べ。",
        "choices": [
            "A. 実験対象を似た条件ごとのブロック（塊）に分けてから各ブロック内で無作為化することで、背景要因の影響を減らすこと",
            "B. 実験を繰り返し行うことで、偶然誤差の影響を大きくすること",
            "C. 複数の要因を同時に操作せず一度に一つずつ試すことで結果を単純化すること",
            "D. 実験データを都合の良いように分類し直して分析すること"
        ],
        "answer_label": "A",
        "answer_index": 0,
        "explanation": "ブロック化（blocking）は、実験対象を外部要因が類似したグループ（ブロック）に分け、各ブロック内で無作為に処理を割り当てる方法です。これにより、ブロック間の差の影響を除去できます。"
    },
    {
        "id": "STAT-019",
        "category": "2変数データ",
        "question": "実験計画や観察研究において交絡要因（コンファウンディング）とは何か。正しい説明を選んでください。",
        "choices": [
            "A. 独立変数（要因）と従属変数に同時に影響を与える要因で、真の因果関係を紛らわしくしてしまうもの",
            "B. 実験の測定誤差のことであり、主効果と交互作用効果を混同させるもの",
            "C. 実験において操作しないで一定に保つ制御変数のこと",
            "D. 観察研究で使われる仮説検定の一種で、因果関係を推定するための手法"
        ],
        "answer_label": "A",
        "answer_index": 0,
        "explanation": "交絡因子（交絡変数）とは、本来調べたい要因と結果の両方に影響を与える隠れた要因のことです。この存在により、本当は原因ではない要因が原因と見誤られる場合があります。"
    },
    {
        "id": "STAT-020",
        "category": "2変数データ",
        "question": "科学実験で「反復（Replication）」を行う主な目的として適切なものはどれか。",
        "choices": [
            "A. 実験結果の偶然によるばらつきを評価し、結果の信頼性を高めるため",
            "B. 実験データを分析する手法を複雑にするため",
            "C. 第1種の過誤を意図的に増やして有意差を出やすくするため",
            "D. 実験条件をすべて一定に保つため"
        ],
        "answer_label": "A",
        "answer_index": 0,
        "explanation": "実験の反復は、偶然誤差による変動を把握し、結果の再現性を確かめるために重要です。"
    },
    {
        "id": "STAT-021",
        "category": "データ収集法",
        "question": "観察研究（観察的研究）と実験研究の違いに関する記述として最も適切なものはどれか。",
        "choices": [
            "A. 実験研究では研究者が被験者へ介入（操作）を行うのに対し、観察研究では研究者は介入せず観察・測定のみ行う",
            "B. 観察研究では原因と結果の因果関係を厳密に特定できるが、実験研究ではできない",
            "C. 実験研究ではデータの収集にランダムサンプリングは用いられない",
            "D. 観察研究は常に実験研究よりも信頼性が高い研究デザインである"
        ],
        "answer_label": "A",
        "answer_index": 0,
        "explanation": "観察研究は、研究者が対象に対して積極的な介入や割り当てをせず、ありのままの状態でデータを観察・収集する研究デザインです。"
    },
    {
        "id": "STAT-022",
        "category": "データ収集法",
        "question": "単純無作為抽出法（Simple Random Sampling）の説明として正しいものを選んでください。",
        "choices": [
            "A. 母集団の全ての要素が等しい確率で選ばれるように無作為に抽出する方法",
            "B. 母集団を層に分けて各層から一定数ずつ抽出する方法",
            "C. ランダムな開始位置を決めて一定間隔ごとに要素を抽出する方法",
            "D. 手近な対象を選ぶなど統計的手続きを用いない抽出方法"
        ],
        "answer_label": "A",
        "answer_index": 0,
        "explanation": "単純無作為抽出法とは、母集団の要素一つひとつがサンプルに選ばれる確率が等しくなるように抽出する方法です。"
    },
    {
        "id": "STAT-023",
        "category": "データ収集法",
        "question": "母集団をいくつかの異なる層（グループ）に分け、各層から無作為にサンプルを抽出する方法はどれか。",
        "choices": [
            "A. 層化抽出法（ストラティファイドサンプリング）",
            "B. 集落抽出法（クラスターサンプリング）",
            "C. 系統抽出法（系統的サンプリング）",
            "D. 雪だるま式抽出法（スノーボールサンプリング）"
        ],
        "answer_label": "A",
        "answer_index": 0,
        "explanation": "層化抽出法は、母集団を予め性質の似たグループ（層）に分割し、各層から無作為にサンプルを取り出す方法です。"
    },
    {
        "id": "STAT-024",
        "category": "データ収集法",
        "question": "ある全国調査で、全国を5つの地域に分けて各地域から1校ずつ中学校を無作為に選び、その選ばれた各学校内の生徒全員を調査対象にした。このような抽出方法を何と呼ぶか。",
        "choices": [
            "A. 集落抽出法（クラスターサンプリング）",
            "B. 層化抽出法（ストラティファイドサンプリング）",
            "C. 系統抽出法（システマティックサンプリング）",
            "D. 単純無作為抽出法（シンプルランダムサンプリング）"
        ],
        "answer_label": "A",
        "answer_index": 0,
        "explanation": "この方法ではまず地域ごとに学校を抽出し、その学校内の全生徒を調べています。これは、学校というクラスター（集落）単位で抽出し、クラスター内の全要素（生徒）を調査する典型的な集落抽出法です。"
    },
    {
        "id": "STAT-025",
        "category": "データ収集法",
        "question": "以下の抽出法のうち、統計的に偏りやすい非確率抽出法の例として最も適切なものはどれか。",
        "choices": [
            "A. 手近な対象からデータを取る便利抽出法（コンビニエンスサンプリング）",
            "B. ランダム番号表を用いた単純無作為抽出法",
            "C. 母集団を細分化し各部分から抽出する層化抽出法",
            "D. 無作為に開始点を決めて一定間隔で抽出する系統抽出法"
        ],
        "answer_label": "A",
        "answer_index": 0,
        "explanation": "便利抽出法とは、調査しやすい対象や入手可能なデータを手当たり次第に集める方法で、統計的な無作為性が確保されないため偏りが生じやすいです。"
    },
    {
        "id": "STAT-026",
        "category": "データ収集法",
        "question": "フィッシャーの「3原則」に含まれないものを選びなさい。",
        "choices": [
            "A. 無作為化（ランダム化）",
            "B. 層別化（ストラティフィケーション）",
            "C. 反復（繰り返し）",
            "D. 局所管理（ブロック化）"
        ],
        "answer_label": "B",
        "answer_index": 1,
        "explanation": "フィッシャーが提唱した実験計画法の三原則は、「無作為化」「反復（復元）」「局所管理（ブロック化）」です。層別化（層化）は標本抽出における手法であり、フィッシャーの実験計画の三原則には含まれません。"
    },
    {
        "id": "STAT-027",
        "category": "データ収集法",
        "question": "統計調査において、標本サイズ（サンプル数）を大きくすると期待できる効果は何か。",
        "choices": [
            "A. 推定や検定の精度が向上し、標本平均や割合の推定区間が狭くなる",
            "B. 系統的誤差（バイアス）が完全になくなる",
            "C. データの母集団分布が正規分布に近づくため標本分散が増大する",
            "D. 第2種過誤（見落としエラー）の確率が上昇する"
        ],
        "answer_label": "A",
        "answer_index": 0,
        "explanation": "一般にサンプル数を増やすと推定の標準誤差が小さくなり、信頼区間が狭く精度が上がります。"
    },
    {
        "id": "STAT-028",
        "category": "データ収集法",
        "question": "統計調査の計画において、調査対象者を事前に割り付けたグループから偏りなく抽出するために重要な手続きはどれか。",
        "choices": [
            "A. 無作為化（ランダム化）",
            "B. 計量化（数値に変換）",
            "C. 標本化率の設定",
            "D. 二重盲検化（ブラインド化）"
        ],
        "answer_label": "A",
        "answer_index": 0,
        "explanation": "ランダム化（無作為抽出・無作為割付）は、標本抽出および実験で偏りを防ぐ最も基本的かつ重要な手続きです。"
    },
    {
        "id": "STAT-029",
        "category": "データ収集法",
        "question": "信頼度99%の信頼区間は、信頼度95%の信頼区間と比べて一般にどうなるか。",
        "choices": [
            "A. 区間の幅が広くなる",
            "B. 区間の幅が狭くなる",
            "C. 区間の中心値（点推定量）が変わる",
            "D. 母平均が区間に含まれる確率が低くなる"
        ],
        "answer_label": "A",
        "answer_index": 0,
        "explanation": "信頼水準を上げる（95% → 99%など）と、より高い確率で真の値を捕捉するために区間の幅は広がります。"
    },
    {
        "id": "STAT-030",
        "category": "データ収集法",
        "question": "無作為化比較試験において、新薬とプラセボの効果差を検定した結果、有意水準5%で有意差が「検出されなかった（p＝0.30）」場合の正しい解釈はどれか。",
        "choices": [
            "A. 「差があるとは言えない」ので、効果差がないと結論づけることはできない",
            "B. 「効果に差がない」と証明されたことを意味する",
            "C. 第1種の誤りを犯した可能性が高いことを意味する",
            "D. 標本サイズを増やせば、有意になったはずだと示唆される"
        ],
        "answer_label": "A",
        "answer_index": 0,
        "explanation": "有意差が検出されなかった場合（p値が有意水準を上回った場合）、「帰無仮説を棄却できない」という結論になります。しかしこれは「効果が同じと証明された」わけではなく、単に「データからは有意な差があると判断できなかった」ことを意味します。"
    },
    {
        "id": "STAT-031",
        "category": "確率",
        "question": "ある試行で事象AまたはBが起こる確率 P(A∪B) を求める公式は次のうちどれか。",
        "choices": [
            "A. P(A) + P(B) - P(A∩B)",
            "B. P(A) + P(B)",
            "C. P(A) × P(B)",
            "D. P(A) - P(B)"
        ],
        "answer_label": "A",
        "answer_index": 0,
        "explanation": "排反でない2事象の和事象の確率は加法定理により P(A∪B) = P(A) + P(B) - P(A∩B) と表されます。"
    },
    {
        "id": "STAT-032",
        "category": "確率",
        "question": "独立な2つの事象AとBに関する正しい関係はどれか。",
        "choices": [
            "A. P(A∩B) = P(A) × P(B)",
            "B. P(A∪B) = P(A) × P(B)",
            "C. P(A∩B) = 0",
            "D. P(A|B) = 1"
        ],
        "answer_label": "A",
        "answer_index": 0,
        "explanation": "独立事象では、一方の起こる確率が他方に影響を与えません。そのため同時に起こる確率は積の形になります (乗法定理)。"
    },
    {
        "id": "STAT-033",
        "category": "確率",
        "question": "P(A)=0.5、P(A∩B)=0.2 のとき、事象Aが起きた条件下で事象Bが起きる確率 P(B|A) を求めよ。",
        "choices": [
            "A. 0.4",
            "B. 0.1",
            "C. 0.25",
            "D. 1.0"
        ],
        "answer_label": "A",
        "answer_index": 0,
        "explanation": "条件付き確率の定義 P(B|A) = P(A∩B) / P(A) を用います。0.2 / 0.5 = 0.4 となります。"
    },
    {
        "id": "STAT-034",
        "category": "確率",
        "question": "袋に赤玉3個、青玉2個が入っている。この袋から2個の玉を無作為に一度に取り出すとき、2個とも赤玉である確率を求めよ（玉は戻さないものとする）。",
        "choices": [
            "A. 3/10 （30%）",
            "B. 2/5 （40%）",
            "C. 1/5 （20%）",
            "D. 1/10 （10%）"
        ],
        "answer_label": "A",
        "answer_index": 0,
        "explanation": "1個目赤: 3/5。2個目赤(残り4個中2個): 2/4=1/2。確率は 3/5 × 1/2 = 3/10 です。"
    },
    {
        "id": "STAT-035",
        "category": "確率",
        "question": "あるテストで、母集団において疾患に罹っている人は1%とする。この疾患の検査は「陽性と出る確率」が、病気の人では90%（感度）、病気でない人では10%（偽陽性率）であるとする。では、ある人がこの検査で陽性となった場合、その人が実際に疾患に罹っている確率（事後確率）に最も近い値を選べ。【ベイズの定理】",
        "choices": [
            "A. 約8%",
            "B. 約50%",
            "C. 約90%",
            "D. 約1%"
        ],
        "answer_label": "A",
        "answer_index": 0,
        "explanation": "ベイズの定理を用いて計算します。P(病気|陽性) = (0.9*0.01) / (0.9*0.01 + 0.1*0.99) ≈ 0.009 / (0.009 + 0.099) = 0.009 / 0.108 ≈ 0.083 (約8.3%)。"
    },
    {
        "id": "STAT-036",
        "category": "確率",
        "question": "コインを3回投げたとき、少なくとも1回表が出る確率を求めよ。",
        "choices": [
            "A. 7/8 （87.5%）",
            "B. 1/8 （12.5%）",
            "C. 3/8 （37.5%）",
            "D. 1/2 （50%）"
        ],
        "answer_label": "A",
        "answer_index": 0,
        "explanation": "「少なくとも1回表」の余事象は「全て裏」。全て裏の確率は (1/2)^3 = 1/8。よって求める確率は 1 - 1/8 = 7/8。"
    },
    {
        "id": "STAT-037",
        "category": "確率",
        "question": "公正なサイコロを2個同時に投げるとき、両方とも6が出る確率を選びなさい。",
        "choices": [
            "A. 1/36",
            "B. 1/12",
            "C. 1/6",
            "D. 1/3"
        ],
        "answer_label": "A",
        "answer_index": 0,
        "explanation": "2個のサイコロは独立なので、それぞれ6が出る確率(1/6)を掛け合わせます。1/6 × 1/6 = 1/36。"
    },
    {
        "id": "STAT-038",
        "category": "確率",
        "question": "互いに排反な（同時には起こらない）2事象AとBについて、正しい関係はどれか。",
        "choices": [
            "A. P(A∩B) = 0",
            "B. P(A∩B) = P(A)P(B)",
            "C. P(A∪B) = 1",
            "D. P(A) = P(B)"
        ],
        "answer_label": "A",
        "answer_index": 0,
        "explanation": "排反事象とは同時には発生しない事象のことです。そのため P(A∩B) = 0 となります。"
    },
    {
        "id": "STAT-039",
        "category": "確率",
        "question": "ベイズの定理は何を計算するのに用いられるか。正しい選択肢を選んでください。",
        "choices": [
            "A. 条件付き確率から事後確率（ある仮説がデータに基づき正しい確率）を求める",
            "B. 母集団から標本を抽出する際の必要標本数を算出する",
            "C. 時系列データにおける移動平均を算出する",
            "D. 相関係数を検定するためのt値を計算する"
        ],
        "answer_label": "A",
        "answer_index": 0,
        "explanation": "ベイズの定理は、事前確率と条件付き確率から事後確率を求めるための公式です。"
    },
    {
        "id": "STAT-040",
        "category": "確率",
        "question": "6面サイコロを1個振ったときの出目Xについて、期待値 E[X] はいくらか。",
        "choices": [
            "A. 3.5",
            "B. 3",
            "C. 3.3…（1/3の逆数）",
            "D. 21"
        ],
        "answer_label": "A",
        "answer_index": 0,
        "explanation": "期待値は (1+2+3+4+5+6)/6 = 21/6 = 3.5 です。"
    },
    {
        "id": "STAT-041",
        "category": "確率分布",
        "question": "二項分布 B(n, p) に従う確率変数Xの分散 V(X) は次のうちどれか。",
        "choices": [
            "A. np(1-p)",
            "B. np",
            "C. np^2",
            "D. p(1-p)"
        ],
        "answer_label": "A",
        "answer_index": 0,
        "explanation": "二項分布の平均は np、分散は np(1-p) です。"
    },
    {
        "id": "STAT-042",
        "category": "確率分布",
        "question": "ポアソン分布 Po(λ) に関する性質として正しいものを選びなさい。",
        "choices": [
            "A. 平均と分散がともに λ で等しい",
            "B. 母集団サイズが小さい場合に使う離散分布である",
            "C. 成功確率pが小さい二項分布とは全く関係がない",
            "D. 連続型の確率分布である"
        ],
        "answer_label": "A",
        "answer_index": 0,
        "explanation": "ポアソン分布は単位時間あたり平均λ回発生するようなまれな事象の発生回数を表す離散分布で、平均=分散=λという関係があります。"
    },
    {
        "id": "STAT-043",
        "category": "確率分布",
        "question": "標準正規分布 N(0, 1) に関する記述として正しいものを選べ。",
        "choices": [
            "A. 平均0、分散1の正規分布である",
            "B. 平均1、分散1の正規分布である",
            "C. 平均0、分散2の正規分布である",
            "D. 平均1、分散0の正規分布である"
        ],
        "answer_label": "A",
        "answer_index": 0,
        "explanation": "標準正規分布は平均0、分散1（標準偏差1）の正規分布です。"
    },
    {
        "id": "STAT-044",
        "category": "確率分布",
        "question": "正規分布 N(μ, σ^2) において、平均値から±1標準偏差の範囲にデータが入る確率はおよそどれくらいか。",
        "choices": [
            "A. 約68%",
            "B. 約95%",
            "C. 約99.7%",
            "D. 約50%"
        ],
        "answer_label": "A",
        "answer_index": 0,
        "explanation": "正規分布では平均±1σに約68%、±2σに約95%、±3σに約99.7%のデータが入ります。"
    },
    {
        "id": "STAT-045",
        "category": "確率分布",
        "question": "指数分布 Ex(λ) の平均（期待値）はどれか。",
        "choices": [
            "A. 1/λ",
            "B. λ",
            "C. λ^2",
            "D. 0"
        ],
        "answer_label": "A",
        "answer_index": 0,
        "explanation": "指数分布の平均は 1/λ、分散は 1/λ^2 となります。"
    },
    {
        "id": "STAT-046",
        "category": "確率分布",
        "question": "次の離散確率分布のうち、「平均と分散が等しい」という関係が成り立つものはどれか。",
        "choices": [
            "A. ポアソン分布",
            "B. 二項分布",
            "C. 超幾何分布",
            "D. 一様分布"
        ],
        "answer_label": "A",
        "answer_index": 0,
        "explanation": "ポアソン分布は平均=分散=λという性質を持ちます。"
    },
    {
        "id": "STAT-047",
        "category": "確率分布",
        "question": "「単位時間あたり平均λ回発生するまれな事象の発生回数」を表す確率分布として適切なのはどれか。",
        "choices": [
            "A. ポアソン分布",
            "B. 二項分布",
            "C. 正規分布",
            "D. 指数分布"
        ],
        "answer_label": "A",
        "answer_index": 0,
        "explanation": "単位時間内のまれな事象の発生回数はポアソン分布でモデル化されることが多いです。"
    },
    {
        "id": "STAT-048",
        "category": "確率分布",
        "question": "幾何分布とはどのような確率分布か。適切な説明を選びなさい。",
        "choices": [
            "A. 確率pで成功する独立試行を繰り返したとき、初めて成功するまでの試行回数の分布",
            "B. 試行回数n回で成功回数がk回となる分布",
            "C. 一定の平均間隔で事象が発生する連続分布",
            "D. 母集団から非復元抽出したときの成功数の分布"
        ],
        "answer_label": "A",
        "answer_index": 0,
        "explanation": "幾何分布は「ベルヌーイ試行（成功確率p）を繰り返したとき、初めて成功が出るまでに要する試行回数」の分布です。"
    },
    {
        "id": "STAT-049",
        "category": "確率分布",
        "question": "母集団のサイズがNで、その中に成功となる要素がK個含まれているとする。復元抽出なしでn個のサンプルを選んだとき、成功要素がx個含まれる確率分布は何か。",
        "choices": [
            "A. 超幾何分布",
            "B. 二項分布",
            "C. ポアソン分布",
            "D. 幾何分布"
        ],
        "answer_label": "A",
        "answer_index": 0,
        "explanation": "超幾何分布は有限母集団から非復元抽出するときの成功数の分布です。"
    },
    {
        "id": "STAT-050",
        "category": "確率分布",
        "question": "大きなnと小さなpにおいて、二項分布 B(n,p) が近似できる確率分布はどれか。",
        "choices": [
            "A. ポアソン分布（λ=np のポアソン）",
            "B. 正規分布（平均np, 分散np(1-p) の正規）",
            "C. 幾何分布（成功確率pの幾何）",
            "D. 超幾何分布（母集団サイズnの超幾何）"
        ],
        "answer_label": "A",
        "answer_index": 0,
        "explanation": "試行回数nが大きく成功確率pが小さい場合、二項分布 B(n,p) は平均λ=npのポアソン分布で近似できます。"
    },
    {
        "id": "STAT-051",
        "category": "標本分布",
        "question": "中心極限定理によれば、母集団の分布に関わらずサンプルサイズが大きいとき、標本平均の分布は近似的に何に従うか。",
        "choices": [
            "A. 正規分布",
            "B. t分布",
            "C. コーシー分布",
            "D. 一様分布"
        ],
        "answer_label": "A",
        "answer_index": 0,
        "explanation": "中心極限定理により、独立同分布のデータから計算した標本平均は、母集団分布の形状に関係なくサンプルサイズが十分大きければ正規分布に近づきます。"
    },
    {
        "id": "STAT-052",
        "category": "標本分布",
        "question": "母分散がσ²である母集団からサンプルサイズnの無作為標本を得たとき、標本平均 X̄ の分散 Var(X̄) はいくらか。",
        "choices": [
            "A. σ²/n",
            "B. σ²",
            "C. σ/√n",
            "D. nσ²"
        ],
        "answer_label": "A",
        "answer_index": 0,
        "explanation": "標本平均の分散は母分散σ²をサンプルサイズnで割った値 σ²/n となります。"
    },
    {
        "id": "STAT-053",
        "category": "標本分布",
        "question": "成功確率pの二項分布 B(n,p) は、nが大きくnpとn(1-p)が十分大きいときに何分布で近似できるか。",
        "choices": [
            "A. 平均 np、分散 np(1-p) の正規分布",
            "B. 平均 np のポアソン分布",
            "C. パラメータpの幾何分布",
            "D. 自由度n-1のカイ二乗分布"
        ],
        "answer_label": "A",
        "answer_index": 0,
        "explanation": "nが大きく、期待値npとnp(1-p)がともに大きければ、二項分布は中心極限定理によりほぼ正規分布に近づきます。"
    },
    {
        "id": "STAT-054",
        "category": "標本分布",
        "question": "母集団が正規分布に従い母分散が未知の場合、母平均の区間推定や検定に用いられる分布はどれか。",
        "choices": [
            "A. t分布（スチューデントのt分布）",
            "B. 標準正規分布",
            "C. カイ二乗分布",
            "D. F分布"
        ],
        "answer_label": "A",
        "answer_index": 0,
        "explanation": "母平均の推定や検定で母分散が未知のとき、標本分散で不偏推定しつつ用いる統計量はt分布に従います。"
    },
    {
        "id": "STAT-055",
        "category": "標本分布",
        "question": "標本分散 s²（自由度ν）について、正規母集団における分散の検定で利用される分布はどれか。",
        "choices": [
            "A. カイ二乗分布（χ²分布）",
            "B. t分布",
            "C. F分布",
            "D. ポアソン分布"
        ],
        "answer_label": "A",
        "answer_index": 0,
        "explanation": "正規母集団のもとで標本分散を適切にスケールするとカイ二乗分布に従います。"
    },
    {
        "id": "STAT-056",
        "category": "標本分布",
        "question": "ある2×3のクロス集計表（2行3列）の独立性のχ²検定を行う場合、検定統計量の自由度はいくつになるか。",
        "choices": [
            "A. 2",
            "B. 1",
            "C. 5",
            "D. 6"
        ],
        "answer_label": "A",
        "answer_index": 0,
        "explanation": "自由度は (行数-1)×(列数-1) = (2-1)×(3-1) = 1×2 = 2 です。"
    },
    {
        "id": "STAT-057",
        "category": "標本分布",
        "question": "標本比例（標本比率） p̂ の標準誤差はどのように表されるか。",
        "choices": [
            "A. √{p(1-p)/n}",
            "B. p(1-p)/n",
            "C. √{np(1-p)}",
            "D. p/√n"
        ],
        "answer_label": "A",
        "answer_index": 0,
        "explanation": "標本比率の標準誤差は √{p(1-p)/n} で表されます。"
    },
    {
        "id": "STAT-058",
        "category": "標本分布",
        "question": "標本サイズnで得た標本平均 X̄ について、その期待値 E[X̄] は母平均とどう関係するか。",
        "choices": [
            "A. 母平均に等しい（標本平均は母平均の不偏推定量）",
            "B. 母平均の1/n倍に等しい",
            "C. 母平均より常に大きくなる傾向がある（正のバイアス）",
            "D. 標本サイズに依存し、nが大きいほど小さくなる"
        ],
        "answer_label": "A",
        "answer_index": 0,
        "explanation": "標本平均の期待値は元の母平均μと等しく、標本平均は母平均の不偏推定量です。"
    },
    {
        "id": "STAT-059",
        "category": "標本分布",
        "question": "正規母集団からの標本に対し算出されるt統計量は、自由度 ν のt分布に従います。この自由度 ν は何によって決まるか。",
        "choices": [
            "A. 標本サイズ n によって n-1 と定まる",
            "B. 母平均や母標準偏差の値によって決まる",
            "C. 選択した有意水準（例えば5%か1%か）によって決まる",
            "D. サンプルのとったt値の大きさによって決まる"
        ],
        "answer_label": "A",
        "answer_index": 0,
        "explanation": "t分布の自由度は、標本の大きさnから1を引いた値になります。"
    },
    {
        "id": "STAT-060",
        "category": "標本分布",
        "question": "F分布はどのような統計量の分布として現れるか。適切な例を選びなさい。",
        "choices": [
            "A. 2つの独立なχ²分布に従う変量の比の分布（分散比の検定や分散分析で利用）",
            "B. 2群の平均値の差の標準化統計量の分布",
            "C. 偏差平方和の平方根の分布",
            "D. コレスポンデンス分析における得点分布"
        ],
        "answer_label": "A",
        "answer_index": 0,
        "explanation": "F分布は2つの独立なカイ二乗統計量の比が従う分布で、母分散の比較（F検定）や分散分析（ANOVA）で用いられます。"
    },
    {
        "id": "STAT-061",
        "category": "推定",
        "question": "統計学における不偏推定量の定義として正しいものはどれか。",
        "choices": [
            "A. 推定量の期待値が真の母数に等しいもの",
            "B. 標本サイズを大きくすると分布が真の値に集中するもの",
            "C. 推定量の標準誤差がゼロになるもの",
            "D. 母集団分布に依存しない推定量のこと"
        ],
        "answer_label": "A",
        "answer_index": 0,
        "explanation": "不偏性とは推定量の期待値が推定対象の真の値に一致する性質を指します。"
    },
    {
        "id": "STAT-062",
        "category": "推定",
        "question": "母分散を推定する際、標本分散の計算で分母を(n-1)で割るのはなぜか。適切な説明を選びなさい。",
        "choices": [
            "A. 標本分散が母分散の不偏推定量となるようにするため",
            "B. 分母をn-1にしないとχ²分布が使えないため",
            "C. 分母をnで割ると常に過大評価になるという経験則から",
            "D. n-1で割った方が計算が簡単になるため"
        ],
        "answer_label": "A",
        "answer_index": 0,
        "explanation": "母分散の推定において、標本分散を用いるのは、これが母分散σ²の不偏推定量となるからです。"
    },
    {
        "id": "STAT-063",
        "category": "推定",
        "question": "一致性（コンシステンシー）を持つ推定量とはどのような推定量か。",
        "choices": [
            "A. 標本サイズを無限に大きくしたとき、真の母数に確率的に収束する推定量",
            "B. 標本分布によらず常に同じ推定値を出す推定量",
            "C. 小標本でも正規分布になるような推定量",
            "D. 標本サイズに関わらずバイアスのない推定量"
        ],
        "answer_label": "A",
        "answer_index": 0,
        "explanation": "一致推定量とは、大標本の極限で真の値に収束する推定量です。"
    },
    {
        "id": "STAT-064",
        "category": "推定",
        "question": "「95%信頼区間」の正しい解釈を選びなさい。",
        "choices": [
            "A. 同じ方法で区間推定を繰り返した場合、その区間が真の値を含む割合がおよそ95%になる",
            "B. この具体的な区間内に真の母数が95%の確率で入っている",
            "C. 母集団の95%がこの区間に収まっている",
            "D. 標本平均の95%がこの区間に入っている"
        ],
        "answer_label": "A",
        "answer_index": 0,
        "explanation": "95%信頼区間とは、同一条件で無数にサンプリングして区間推定を行ったときに約95%の頻度で真の母数を含む区間が得られる、という意味です。"
    },
    {
        "id": "STAT-065",
        "category": "推定",
        "question": "すべての条件を一定にした場合、標本サイズを増やすと母平均の信頼区間の幅はどう変化するか。",
        "choices": [
            "A. 狭くなる（推定精度が上がる）",
            "B. 広くなる",
            "C. 変わらない",
            "D. 信頼水準に依存するため一概に言えない"
        ],
        "answer_label": "A",
        "answer_index": 0,
        "explanation": "サンプル数を増やすほど標本平均の標準誤差が小さくなるため、信頼区間の幅は狭くなります。"
    },
    {
        "id": "STAT-066",
        "category": "推定",
        "question": "母平均の信頼区間を計算する際、母分散が未知の場合にはどのように対応するか。",
        "choices": [
            "A. t分布を用いて信頼区間を求める",
            "B. 母分散が分かるまで信頼区間は計算できない",
            "C. 標本分散の平方根で母分散の代わりをするが、計算式は変わらない",
            "D. 区間の中心ではなく両端を標本中央値に置き換える"
        ],
        "answer_label": "A",
        "answer_index": 0,
        "explanation": "母分散未知のとき、母平均の信頼区間ではt分布を用いる必要があります。"
    },
    {
        "id": "STAT-067",
        "category": "推定",
        "question": "ある標本で平均50、標準誤差が4でした。95%信頼区間を近似的に求めると次のどれになるか（95%信頼係数≈1.96とする）。",
        "choices": [
            "A. 約 (42, 58)",
            "B. 約 (46, 54)",
            "C. 約 (38, 62)",
            "D. 約 (40, 60)"
        ],
        "answer_label": "A",
        "answer_index": 0,
        "explanation": "信頼区間は 50 ± 1.96×4 ≈ 50 ± 7.84 ですので、およそ (42, 58) と求まります。"
    },
    {
        "id": "STAT-068",
        "category": "推定",
        "question": "母分散の信頼区間を求める際に利用される分布はどれか。",
        "choices": [
            "A. カイ二乗分布",
            "B. t分布",
            "C. F分布",
            "D. 正規分布"
        ],
        "answer_label": "A",
        "answer_index": 0,
        "explanation": "母分散σ²の信頼区間推定には、標本分散とカイ二乗分布を用いた方法を取ります。"
    },
    {
        "id": "STAT-069",
        "category": "推定",
        "question": "2つの不偏推定量AとBがあるとします。両者とも不偏性を持つ場合、より効率的（望ましい）な推定量と言えるのはどちらか。",
        "choices": [
            "A. 分散（ばらつき）がより小さい推定量",
            "B. 計算手順がより簡単な推定量",
            "C. 標本サイズによる変動が大きい推定量",
            "D. 理論的背景がより複雑な推定量"
        ],
        "answer_label": "A",
        "answer_index": 0,
        "explanation": "2つの推定量がともに不偏なら、通常は分散（標準誤差）がより小さい方を効率的な推定量とみなします。"
    },
    {
        "id": "STAT-070",
        "category": "推定",
        "question": "母分散未知の正規母集団に対し、母平均の検定を行う場合に用いる検定統計量はどの分布に従うか。",
        "choices": [
            "A. t分布に従う（自由度n-1）",
            "B. 標準正規分布に従う",
            "C. カイ二乗分布に従う（自由度n-1）",
            "D. コーシー分布に従う"
        ],
        "answer_label": "A",
        "answer_index": 0,
        "explanation": "母平均の検定では、母分散が未知の場合t分布を使用します。"
    },
    {
        "id": "STAT-071",
        "category": "仮説検定",
        "question": "有意水準5%である仮説検定において、計算されたp値が0.02であった。正しい結論はどれか。",
        "choices": [
            "A. 帰無仮説を棄却し、対立仮説を採択する",
            "B. 帰無仮説を採択する",
            "C. 対立仮説を棄却する",
            "D. 結論は得られない（有意差なしと判断）"
        ],
        "answer_label": "A",
        "answer_index": 0,
        "explanation": "p値0.02は有意水準5%より小さいため、統計的に有意と判断され、帰無仮説を棄却します。"
    },
    {
        "id": "STAT-072",
        "category": "仮説検定",
        "question": "2つの独立な母集団の平均の差を調べる際に用いる検定はどれか（母分散は未知だが等しいと仮定できる場合）。",
        "choices": [
            "A. 2標本t検定（スチューデントのt検定）",
            "B. 対応のあるt検定",
            "C. カイ二乗検定",
            "D. 検定はできない"
        ],
        "answer_label": "A",
        "answer_index": 0,
        "explanation": "2群の平均値の差の検定には2標本t検定を用います。"
    },
    {
        "id": "STAT-073",
        "category": "仮説検定",
        "question": "母分散が既知である場合の母平均の検定統計量はどれか。",
        "choices": [
            "A. 標準正規分布に従うZ統計量",
            "B. t分布に従うt統計量",
            "C. χ²統計量",
            "D. F統計量"
        ],
        "answer_label": "A",
        "answer_index": 0,
        "explanation": "母分散既知の仮説検定では、Z検定を行います。"
    },
    {
        "id": "STAT-074",
        "category": "仮説検定",
        "question": "仮説検定における第1種の誤りとは何か。",
        "choices": [
            "A. 本当は帰無仮説が正しいのにそれを棄却してしまう誤り（偽陽性）",
            "B. 本当は対立仮説が正しいのに帰無仮説を棄却しない誤り（偽陰性）",
            "C. 母分散が既知なのに未知と仮定して検定してしまう誤り",
            "D. 検定統計量の計算を間違える誤り"
        ],
        "answer_label": "A",
        "answer_index": 0,
        "explanation": "第1種の過誤とは、「帰無仮説が真であるにもかかわらず、それを誤って棄却してしまう誤り」です。"
    },
    {
        "id": "STAT-075",
        "category": "仮説検定",
        "question": "仮説検定における第2種の誤りとは何か。",
        "choices": [
            "A. 本当は対立仮説が正しいのに帰無仮説を棄却しない誤り（偽陰性）",
            "B. 本当は帰無仮説が正しいのにそれを棄却する誤り（偽陽性）",
            "C. 検定において検出力が過剰に高すぎることによる誤り",
            "D. 標本サイズを間違えて設定したことによる誤り"
        ],
        "answer_label": "A",
        "answer_index": 0,
        "explanation": "第2種の過誤とは「帰無仮説が偽（対立仮説が真）であるにも関わらず、誤って帰無仮説を棄却し損なう誤り」です。"
    },
    {
        "id": "STAT-076",
        "category": "仮説検定",
        "question": "p値（P-value）の正しい説明はどれか。",
        "choices": [
            "A. 帰無仮説が正しいと仮定したとき、現在の観測結果以上に極端な結果が得られる確率",
            "B. 帰無仮説が真である確率そのもの",
            "C. 対立仮説が真である確率",
            "D. 第1種誤りを犯す確率（有意水準と同義）"
        ],
        "answer_label": "A",
        "answer_index": 0,
        "explanation": "p値とは、「帰無仮説が正しいと仮定した場合に、今得られた統計量の値（あるいはそれより極端な値）が観測される確率」を指します。"
    },
    {
        "id": "STAT-077",
        "category": "仮説検定",
        "question": "有意水準5%とは何を意味するか。",
        "choices": [
            "A. 帰無仮説が本当は正しいのに棄却してしまう誤りの確率を5%に定めたということ",
            "B. 帰無仮説が正しい確率が5%であるということ",
            "C. 対立仮説が正しい確率を95%と見なすこと",
            "D. 検定統計量が5%水準で有意になること"
        ],
        "answer_label": "A",
        "answer_index": 0,
        "explanation": "有意水準αとは、「第1種の誤りを犯す確率をαに抑える」ように検定の境界を設定することです。"
    },
    {
        "id": "STAT-078",
        "category": "仮説検定",
        "question": "2×2の分割表において、カイ二乗検定の期待度数が全セルで5以上であることが推奨される理由として適切なのはどれか。",
        "choices": [
            "A. 期待度数が小さいと近似的なχ²分布による検定結果の信頼性が低下するため",
            "B. 期待度数が5未満だとχ²値が常に0になってしまうため",
            "C. 観測度数との比率が整数で表せなくなるため",
            "D. 母集団のサイズ推定が不可能になるため"
        ],
        "answer_label": "A",
        "answer_index": 0,
        "explanation": "期待度数が小さいとχ²近似の信頼性が下がるため、その場合はフィッシャーの正確検定などが推奨されます。"
    },
    {
        "id": "STAT-079",
        "category": "仮説検定",
        "question": "カイ二乗検定で計算される期待度数（期待頻度）の求め方として正しい式はどれか。",
        "choices": [
            "A. (行合計 × 列合計) / 総合計",
            "B. (行合計 + 列合計) / 2",
            "C. 観測度数 / 総合計",
            "D. 行割合 × 列割合"
        ],
        "answer_label": "A",
        "answer_index": 0,
        "explanation": "カイ二乗独立性検定の期待度数は (該当行の合計×該当列の合計)/総合計 で与えられます。"
    },
    {
        "id": "STAT-080",
        "category": "仮説検定",
        "question": "カイ二乗検定統計量が大きな値になればなるほど、どのような結論になるか。",
        "choices": [
            "A. 帰無仮説を棄却する傾向が強まる（p値が小さくなる）",
            "B. 帰無仮説を棄却しにくくなる（p値が大きくなる）",
            "C. 母集団サイズが大きい可能性があると判断する",
            "D. 検定結果には影響しない"
        ],
        "answer_label": "A",
        "answer_index": 0,
        "explanation": "カイ二乗値が大きいほど「ずれが大きい＝帰無仮説の仮定から外れている」ことを意味し、p値は小さくなります。"
    },
    {
        "id": "STAT-081",
        "category": "カイ二乗検定",
        "question": "あるサイコロを60回振ったところ、出目の頻度が1:8回、2:12回、3:11回、4:10回、5:9回、6:10回であった。このサイコロが「理論的には各目が等確率」と仮定したとき、適合度のχ²検定の自由度はいくつか。",
        "choices": [
            "A. 5",
            "B. 6",
            "C. 59",
            "D. 60"
        ],
        "answer_label": "A",
        "answer_index": 0,
        "explanation": "カテゴリ数は6（目の数）で、各目の確率は等しいと完全に既知なので自由度=6-1=5となります。"
    },
    {
        "id": "STAT-082",
        "category": "カイ二乗検定",
        "question": "2×2の分割表について、カイ二乗独立性検定の帰無仮説はどのような内容か。",
        "choices": [
            "A. 2つのカテゴリ変数が独立である（関連がない）という仮説",
            "B. 2つのカテゴリ変数が従属関係にあるという仮説",
            "C. 行合計と列合計が等しいという仮説",
            "D. 期待度数と観測度数が完全に一致しているという仮説"
        ],
        "answer_label": "A",
        "answer_index": 0,
        "explanation": "独立性のχ²検定では、「行と列の変数に関連性がない（独立である）」を帰無仮説とします。"
    },
    {
        "id": "STAT-083",
        "category": "カイ二乗検定",
        "question": "期待度数が5未満のセルが多く存在するような場合、独立性のχ²検定ではどのような対応が推奨されるか。",
        "choices": [
            "A. カイ二乗検定の適用条件を満たさないので、フィッシャーの正確確率検定など別の手法を用いる",
            "B. とりあえずχ²検定を実施して、結果のp値に5%を加算補正する",
            "C. 観測度数が5以上になるよう母集団サイズNを増やす",
            "D. 帰無仮説を棄却しないことにする（有意ではないと見なす）"
        ],
        "answer_label": "A",
        "answer_index": 0,
        "explanation": "期待度数が小さい場合はフィッシャーの正確検定など期待度数に依存しない方法を使うことが推奨されます。"
    },
    {
        "id": "STAT-084",
        "category": "カイ二乗検定",
        "question": "カイ二乗検定においてχ²値 = 0となるのはどんな場合か。",
        "choices": [
            "A. 観測度数と期待度数が完全に一致する場合",
            "B. 観測度数の総和がゼロの場合",
            "C. 自由度がゼロの場合",
            "D. 検定統計量の計算途中で丸め誤差が出た場合"
        ],
        "answer_label": "A",
        "answer_index": 0,
        "explanation": "χ²値は「観測度数と期待度数のずれ」の指標なので、完全に一致すれば0になります。"
    },
    {
        "id": "STAT-085",
        "category": "カイ二乗検定",
        "question": "2×2分割表の独立性のχ²検定を行ったところ、p値は0.20であった。正しい解釈はどれか。",
        "choices": [
            "A. 有意水準5%では帰無仮説を棄却できない（独立でないとは言えない）",
            "B. 2つの変数の間には強い関係がある",
            "C. 第2種の誤りが起きたと判断する",
            "D. 期待度数の推定に問題があった可能性がある"
        ],
        "answer_label": "A",
        "answer_index": 0,
        "explanation": "p=0.20は有意水準5%を上回るため、帰無仮説（独立である）を棄却しません。"
    },
    {
        "id": "STAT-086",
        "category": "カイ二乗検定",
        "question": "適合度のχ²検定とは何を検定するものか。",
        "choices": [
            "A. 観測されたカテゴリーデータが理論上の分布によく一致しているか（適合しているか）を検定する",
            "B. 2つの質的変数に関連があるかを検定する",
            "C. 母平均が特定の値に等しいかを検定する",
            "D. 2つの母分散が等しいかを検定する"
        ],
        "answer_label": "A",
        "answer_index": 0,
        "explanation": "適合度検定は、データの分布がある仮定された理論分布に従っているかどうかを調べるものです。"
    },
    {
        "id": "STAT-087",
        "category": "カイ二乗検定",
        "question": "ある適合度検定の結果、χ²統計量=10.5、自由度=5であった。このとき得られるp値はおおよそどの範囲になるか（※χ²(5)分布の上側5%点は11.07、上側10%点は9.24）。",
        "choices": [
            "A. 0.05 < p < 0.10",
            "B. p < 0.01",
            "C. 0.10 < p < 0.20",
            "D. p ≈ 0.95"
        ],
        "answer_label": "A",
        "answer_index": 0,
        "explanation": "χ²=10.5は上側5%点(11.07)より小さく、上側10%点(9.24)より大きいため、p値は0.05～0.10の間です。"
    },
    {
        "id": "STAT-088",
        "category": "カイ二乗検定",
        "question": "ある4×3の分割表について、独立性の検定をしたところχ²値=16.0、自由度=6であった（有意水準5%におけるχ²の臨界値=12.59(ν=6)）。正しい判断はどれか。",
        "choices": [
            "A. 帰無仮説を棄却し、行と列の変数には有意な関係があると判断する",
            "B. 帰無仮説を棄却できず、独立であると判断する",
            "C. p値は約0.20である",
            "D. 自由度の設定を間違えているため判断不可である"
        ],
        "answer_label": "A",
        "answer_index": 0,
        "explanation": "統計量16.0が臨界値12.59を上回っているため、帰無仮説（独立）は棄却されます。"
    },
    {
        "id": "STAT-089",
        "category": "カイ二乗検定",
        "question": "自由度(k=3)のカイ二乗分布の形状について正しいのはどれか。",
        "choices": [
            "A. 左に裾が短く、右に裾が長い（正の歪度を持つ）分布",
            "B. 平均0を中心に左右対称な分布",
            "C. -∞～+∞まで定義される両側分布",
            "D. kが小さいほど正規分布に近づく"
        ],
        "answer_label": "A",
        "answer_index": 0,
        "explanation": "カイ二乗分布は0以上で定義され、非対称に右に裾が長い形状をしています。"
    },
    {
        "id": "STAT-090",
        "category": "カイ二乗検定",
        "question": "適合度検定を行う際、仮説となる理論分布に未知パラメータが含まれる場合はどう対処するか。",
        "choices": [
            "A. パラメータを推定してから、その分だけ自由度を減らしてχ²分布を用いる",
            "B. パラメータが未知なら適合度検定は実行できない",
            "C. パラメータの事前分布を設定してベイズ推定を行う",
            "D. 理論分布ではなくノンパラメトリックな検定に切り替える"
        ],
        "answer_label": "A",
        "answer_index": 0,
        "explanation": "適合度検定で理論分布のパラメータが未知の場合、標本から推定し、その推定に使った自由度分だけカイ二乗分布の自由度を減らします。"
    },
    {
        "id": "STAT-091",
        "category": "線形モデル",
        "question": "分散分析（ANOVA）は主に何を比較するための手法か。",
        "choices": [
            "A. 3つ以上の母集団の平均値の差を一括して検定するため",
            "B. 複数の母集団の分散が等しいかどうかを検定するため",
            "C. 質的変数間の連関を検定するため",
            "D. 時系列データの分散が一定かどうかを検定するため"
        ],
        "answer_label": "A",
        "answer_index": 0,
        "explanation": "分散分析は、要因水準間の差など複数グループの平均を同時に比較するための方法です。"
    },
    {
        "id": "STAT-092",
        "category": "線形モデル",
        "question": "分散分析における帰無仮説として正しいものを選べ。",
        "choices": [
            "A. すべての群の母平均が等しい",
            "B. すべての群の母分散が等しい",
            "C. 少なくとも一つの群の平均が異なる",
            "D. 主効果が存在しないが交互作用効果は存在する"
        ],
        "answer_label": "A",
        "answer_index": 0,
        "explanation": "分散分析の基本的な帰無仮説は「比較している複数群の母平均は全て等しい」です。"
    },
    {
        "id": "STAT-093",
        "category": "線形モデル",
        "question": "回帰分析において、回帰係数の有意性を検定する際に用いる統計手法は何か。",
        "choices": [
            "A. t検定（各回帰係数についてのt値）",
            "B. カイ二乗検定",
            "C. Z検定",
            "D. 一元配置分散分析"
        ],
        "answer_label": "A",
        "answer_index": 0,
        "explanation": "回帰分析では各回帰係数がゼロと異なるか（有意か）を調べるために、t検定を行います。"
    },
    {
        "id": "STAT-094",
        "category": "線形モデル",
        "question": "単回帰分析の結果、決定係数 R² が0.95であった。正しい解釈はどれか。",
        "choices": [
            "A. 説明変数が目的変数の変動を約95%説明している",
            "B. 回帰式の予測精度が5%しかない",
            "C. 予測値と残差の相関が0.95である",
            "D. 回帰係数のp値が0.05である"
        ],
        "answer_label": "A",
        "answer_index": 0,
        "explanation": "決定係数R²は「目的変数の分散のうち説明変数で説明できた割合」を表します。"
    },
    {
        "id": "STAT-095",
        "category": "線形モデル",
        "question": "回帰分析において残差プロットをチェックする主な目的は何か。",
        "choices": [
            "A. 回帰の仮定（線形性・等分散性・正規性）の妥当性を視覚的に確認するため",
            "B. 相関係数の値を算出するため",
            "C. 決定係数を最大化するために外れ値を除外すること",
            "D. 新しい予測に残差を加えて精度を上げるため"
        ],
        "answer_label": "A",
        "answer_index": 0,
        "explanation": "残差プロットを調べることで、線形モデルの前提（残差にパターンがないか、等分散か等）を確認できます。"
    },
    {
        "id": "STAT-096",
        "category": "線形モデル",
        "question": "実験計画法において、交互作用効果とは何か。",
        "choices": [
            "A. 2つ以上の因子が組み合わさったとき、それぞれ単独の効果では説明できない相乗/相殺的な効果が現れること",
            "B. 要因の主効果が存在しない場合にのみ現れる見かけ上の効果",
            "C. 実験を繰り返し行うことで減少する誤差項のこと",
            "D. ブロック内でのみ生じる特殊な効果のこと"
        ],
        "answer_label": "A",
        "answer_index": 0,
        "explanation": "交互作用効果とは、複数の要因がある場合に、ある要因の効果が他の要因の水準によって変化する現象です。"
    },
    {
        "id": "STAT-097",
        "category": "線形モデル",
        "question": "重回帰分析で説明変数を増やすと、通常決定係数 R² の値はどうなるか。",
        "choices": [
            "A. 大きくなる（減少はしない）",
            "B. 小さくなる",
            "C. 変わらない",
            "D. 目的変数との相関次第で増減する"
        ],
        "answer_label": "A",
        "answer_index": 0,
        "explanation": "決定係数R²は説明変数を追加すると単調非減少です。"
    },
    {
        "id": "STAT-098",
        "category": "線形モデル",
        "question": "線形モデル（重回帰）における多重共線性とは何か。",
        "choices": [
            "A. 説明変数同士が強い相関を持っている状態で、推定が不安定になる問題",
            "B. 目的変数が正規分布から大きく外れている状態",
            "C. 外れ値が多数存在する状態",
            "D. 説明変数がカテゴリー変数ばかりである状態"
        ],
        "answer_label": "A",
        "answer_index": 0,
        "explanation": "多重共線性とは、説明変数同士が高い相関を持つため、回帰係数の推定が不安定になる問題です。"
    },
    {
        "id": "STAT-099",
        "category": "線形モデル",
        "question": "ダミー変数とは何か。適切な説明を選べ。",
        "choices": [
            "A. 質的なカテゴリー変数を0/1の数値に置き換えた変数",
            "B. 外れ値を表すために作る特別な変数",
            "C. 計算ミスを検出するために入れる架空の変数",
            "D. 多重共線性を解消するために追加する変数"
        ],
        "answer_label": "A",
        "answer_index": 0,
        "explanation": "ダミー変数は、カテゴリー（質的）データを数量化するために用いる変数です。"
    },
    {
        "id": "STAT-100",
        "category": "線形モデル",
        "question": "対照群（コントロール群）とは実験計画において何か。",
        "choices": [
            "A. 処置（介入）を施さず基準として比較するグループ",
            "B. 実験条件をすべて組み合わせた完全な群",
            "C. 実験を二重盲検化する際の比較対象となるグループ",
            "D. データ収集を行わないプラセボ効果除去のための群"
        ],
        "answer_label": "A",
        "answer_index": 0,
        "explanation": "対照群とは、実験で何らかの処置を行う「処置群」に対して、処置を行わず比較基準とするグループです。"
    }
]